cancer_analysis/__init__.py
cancer_analysis/analysis/__init__.py
cancer_analysis/analysis/statistics.py
cancer_analysis/analysis/visualization.py
cancer_analysis/data/__init__.py
cancer_analysis/data/loaders.py
cancer_analysis/data/preprocessors.py
cancer_analysis/data/validators.py
cancer_analysis/models/__init__.py
cancer_analysis/models/base.py
cancer_analysis/models/classifiers.py
cancer_analysis/models/predictors.py
cancer_analysis/utils/__init__.py
cancer_analysis/utils/config.py
cancer_analysis/utils/helpers.py
cancer_clinical_data_analysis-0.1.1.dist-info/METADATA
cancer_clinical_data_analysis-0.1.1.dist-info/WHEEL
cancer_clinical_data_analysis-0.1.1.dist-info/entry_points.txt
cancer_clinical_data_analysis-0.1.1.dist-info/licenses/LICENSE.md
cancer_clinical_data_analysis-0.1.1.dist-info/RECORD
