Metadata-Version: 2.4
Name: cancer-clinical-data-analysis
Version: 0.1.1
Summary: A comprehensive Python package for cancer clinical data analysis including data processing, statistical analysis, survival modeling, and visualization
Project-URL: Homepage, https://codebase.helmholtz.cloud/tud-rse-pojects-2025/group-10
Project-URL: Repository, https://codebase.helmholtz.cloud/tud-rse-pojects-2025/group-10
Author-email: Zaeem Asghar <zaeem.asghar@mailbox.tu-dresden.de>, Zoha Rashid <zoha.rashid@mailbox.tu-dresden.de>
License: MIT License
License-File: LICENSE.md
Keywords: bioinformatics,cancer,clinical-data,machine-learning,survival-analysis
Classifier: Development Status :: 3 - Alpha
Classifier: Intended Audience :: Healthcare Industry
Classifier: Intended Audience :: Science/Research
Classifier: License :: OSI Approved :: MIT License
Classifier: Operating System :: OS Independent
Classifier: Programming Language :: Python :: 3
Classifier: Programming Language :: Python :: 3.11
Classifier: Programming Language :: Python :: 3.12
Classifier: Topic :: Scientific/Engineering :: Bio-Informatics
Classifier: Topic :: Scientific/Engineering :: Medical Science Apps.
Requires-Python: >=3.11
Requires-Dist: click>=8.1.0
Requires-Dist: lifelines>=0.27.0
Requires-Dist: matplotlib>=3.6.0
Requires-Dist: numpy>=2.3.1
Requires-Dist: pandas>=2.3.1
Requires-Dist: pytest>=8.4.1
Requires-Dist: requests>=2.28.0
Requires-Dist: scikit-learn>=1.2.0
Requires-Dist: scipy>=1.10.0
Requires-Dist: seaborn>=0.12.0
Provides-Extra: dev
Requires-Dist: bandit>=1.7.0; extra == 'dev'
Requires-Dist: black>=23.1.0; extra == 'dev'
Requires-Dist: pre-commit>=3.0.0; extra == 'dev'
Requires-Dist: pytest-cov>=4.0.0; extra == 'dev'
Requires-Dist: pytest-mock>=3.10.0; extra == 'dev'
Requires-Dist: pytest>=7.2.0; extra == 'dev'
Requires-Dist: ruff>=0.1.0; extra == 'dev'
Provides-Extra: docs
Requires-Dist: sphinx-rtd-theme>=1.2.0; extra == 'docs'
Requires-Dist: sphinx>=6.0.0; extra == 'docs'
Provides-Extra: jupyter
Requires-Dist: ipython>=8.0.0; extra == 'jupyter'
Requires-Dist: jupyter>=1.0.0; extra == 'jupyter'
Requires-Dist: plotly>=5.13.0; extra == 'jupyter'
Requires-Dist: statsmodels>=0.13.0; extra == 'jupyter'
